actionlib_msgs/__init__.py
actionlib_msgs/msg/_GoalID.py
actionlib_msgs/msg/_GoalStatus.py
actionlib_msgs/msg/_GoalStatusArray.py
actionlib_msgs/msg/__init__.py
catkin/__init__.py
catkin/builder.py
catkin/cmake.py
catkin/environment_cache.py
catkin/find_in_workspaces.py
catkin/init_workspace.py
catkin/package_version.py
catkin/terminal_color.py
catkin/test_results.py
catkin/tidy_xml.py
catkin/workspace.py
catkin/workspace_vcs.py
control_msgs/__init__.py
control_msgs/msg/_FollowJointTrajectoryAction.py
control_msgs/msg/_FollowJointTrajectoryActionFeedback.py
control_msgs/msg/_FollowJointTrajectoryActionGoal.py
control_msgs/msg/_FollowJointTrajectoryActionResult.py
control_msgs/msg/_FollowJointTrajectoryFeedback.py
control_msgs/msg/_FollowJointTrajectoryGoal.py
control_msgs/msg/_FollowJointTrajectoryResult.py
control_msgs/msg/_GripperCommand.py
control_msgs/msg/_GripperCommandAction.py
control_msgs/msg/_GripperCommandActionFeedback.py
control_msgs/msg/_GripperCommandActionGoal.py
control_msgs/msg/_GripperCommandActionResult.py
control_msgs/msg/_GripperCommandFeedback.py
control_msgs/msg/_GripperCommandGoal.py
control_msgs/msg/_GripperCommandResult.py
control_msgs/msg/_JointControllerState.py
control_msgs/msg/_JointJog.py
control_msgs/msg/_JointTolerance.py
control_msgs/msg/_JointTrajectoryAction.py
control_msgs/msg/_JointTrajectoryActionFeedback.py
control_msgs/msg/_JointTrajectoryActionGoal.py
control_msgs/msg/_JointTrajectoryActionResult.py
control_msgs/msg/_JointTrajectoryControllerState.py
control_msgs/msg/_JointTrajectoryFeedback.py
control_msgs/msg/_JointTrajectoryGoal.py
control_msgs/msg/_JointTrajectoryResult.py
control_msgs/msg/_PidState.py
control_msgs/msg/_PointHeadAction.py
control_msgs/msg/_PointHeadActionFeedback.py
control_msgs/msg/_PointHeadActionGoal.py
control_msgs/msg/_PointHeadActionResult.py
control_msgs/msg/_PointHeadFeedback.py
control_msgs/msg/_PointHeadGoal.py
control_msgs/msg/_PointHeadResult.py
control_msgs/msg/_SingleJointPositionAction.py
py3rosmsgs-1.18.dist-info/METADATA
py3rosmsgs-1.18.dist-info/WHEEL
py3rosmsgs-1.18.dist-info/top_level.txt
py3rosmsgs-1.18.dist-info/RECORD
