Metadata-Version: 2.1
Name: py3rosmsgs
Version: 1.18
Summary: Python 3 Port of ROS 1.0 messages from genpy generated python classes and pre-compiled binaries.
Home-page: UNKNOWN
Author: Rahul Bhadani
Author-email: rahulbhadani@email.arizona.edu
License: UNKNOWN
Keywords: autonomous vehicle,ACC,adaptive cruise control,robotics,ros,visualization
Platform: UNKNOWN
Classifier: Programming Language :: Python :: 3
Classifier: Framework :: Robot Framework
Classifier: Topic :: Scientific/Engineering :: Visualization
Classifier: License :: OSI Approved :: MIT License
Requires-Dist: gnupg
Requires-Dist: matplotlib
Requires-Dist: numpy
Requires-Dist: pathlib
Requires-Dist: pyserial
